GmailAutoReply.py
setup.py
garforprudence.egg-info/PKG-INFO
garforprudence.egg-info/SOURCES.txt
garforprudence.egg-info/dependency_links.txt
garforprudence.egg-info/entry_points.txt
garforprudence.egg-info/requires.txt
garforprudence.egg-info/top_level.txt