Metadata-Version: 1.0
Name: garforprudence
Version: 0.0.1a3
Summary: An example distribution
Home-page: https://github.com/tychenjiajun
Author: tychenjiajun
Author-email: tychenjiajun@163.com
License: MIT License
Keywords: python gmail
Platform: UNKNOWN
